fitfix/__init__.py
fitfix/fitfix.py
fitfix-0.1.0.dist-info/licenses/LICENSE
fitfix-0.1.0.dist-info/WHEEL
fitfix-0.1.0.dist-info/entry_points.txt
fitfix-0.1.0.dist-info/METADATA
fitfix-0.1.0.dist-info/RECORD
