Metadata-Version: 2.4
Name: fitfix
Version: 0.1.0
Summary: Fixes small issues of FIT files generated by Tymewear
Author: Dominik Rappaport
Author-email: Dominik Rappaport <dominik@rappaport.at>
License-Expression: MIT
License-File: LICENSE
Requires-Dist: fit-tool>=0.9.13
Requires-Python: >=3.10
Project-URL: Homepage, https://github.com/dominikrappaport/FITFixer
Project-URL: Issues, https://github.com/dominikrappaport/FITFixer/issues
